kadaptest2/__init__.py
kadaptest2/data.py
kadaptest2/vin_decoder/__init__.py
kadaptest2/vin_decoder/decoder.py
kadaptest2-0.0.0.dist-info/LICENSE
kadaptest2-0.0.0.dist-info/METADATA
kadaptest2-0.0.0.dist-info/WHEEL
kadaptest2-0.0.0.dist-info/top_level.txt
kadaptest2-0.0.0.dist-info/RECORD
